pyarmor/cli/runtime/__init__.py
pyarmor/cli/runtime/libs/alpine.aarch64/pyarmor_runtime.so
pyarmor/cli/runtime/libs/alpine.x86_64/pyarmor_runtime.so
pyarmor/cli/runtime/libs/android.aarch64/pyarmor_runtime.so
pyarmor/cli/runtime/libs/android.armv7/pyarmor_runtime.so
pyarmor/cli/runtime/libs/android.x86/pyarmor_runtime.so
pyarmor/cli/runtime/libs/android.x86_64/pyarmor_runtime.so
pyarmor/cli/runtime/libs/darwin.arm64/pyarmor_runtime.so
pyarmor/cli/runtime/libs/darwin.x86_64/pyarmor_runtime.so
pyarmor/cli/runtime/libs/freebsd.x86_64/pyarmor_runtime.so
pyarmor/cli/runtime/libs/linux.aarch64/pyarmor_runtime.so
pyarmor/cli/runtime/libs/linux.armv7/pyarmor_runtime.so
pyarmor/cli/runtime/libs/linux.x86/pyarmor_runtime.so
pyarmor/cli/runtime/libs/linux.x86_64/pyarmor_runtime.so
pyarmor/cli/runtime/libs/windows.x86/pyarmor_runtime.pyd
pyarmor/cli/runtime/libs/windows.x86/themida/pyarmor_runtime.pyd
pyarmor/cli/runtime/libs/windows.x86_64/pyarmor_runtime.pyd
pyarmor/cli/runtime/libs/windows.x86_64/themida/pyarmor_runtime.pyd
pyarmor.cli.runtime-3.2.5.dist-info/METADATA
pyarmor.cli.runtime-3.2.5.dist-info/WHEEL
pyarmor.cli.runtime-3.2.5.dist-info/top_level.txt
pyarmor.cli.runtime-3.2.5.dist-info/RECORD
