Metadata-Version: 2.1
Name: pyarmor.cli.runtime
Version: 3.2.5
Summary: Provide binary modules for cross-platform obfuscation
Home-page: https://github.com/dashingsoft/pyarmor
Author: Jondy Zhao
Author-email: pyarmor@163.com
License: Free To Use But Restricted
Keywords: protect obfuscate encrypt obfuscation distribute
Platform: UNKNOWN
Classifier: Programming Language :: Python :: 3
Classifier: License :: Free To Use But Restricted
Classifier: Operating System :: MacOS
Classifier: Operating System :: Microsoft :: Windows
Classifier: Operating System :: POSIX
Classifier: Intended Audience :: Developers
Classifier: Topic :: Software Development :: Build Tools
Classifier: Topic :: Utilities
Classifier: Topic :: Security
Classifier: Topic :: System :: Software Distribution
